LICENSE.txt
MANIFEST.in
README.md
setup.py
GooeyDev.egg-info/PKG-INFO
GooeyDev.egg-info/SOURCES.txt
GooeyDev.egg-info/dependency_links.txt
GooeyDev.egg-info/requires.txt
GooeyDev.egg-info/top_level.txt
gooey/__init__.py
gooey/__main__.py
gooey/gui/__init__.py
gooey/gui/application.py
gooey/gui/cli.py
gooey/gui/events.py
gooey/gui/formatters.py
gooey/gui/image_repository.py
gooey/gui/imageutil.py
gooey/gui/processor.py
gooey/gui/pubsub.py
gooey/gui/seeder.py
gooey/gui/three_to_four.py
gooey/gui/validators.py
gooey/gui/components/__init__.py
gooey/gui/components/config.py
gooey/gui/components/console.py
gooey/gui/components/footer.py
gooey/gui/components/header.py
gooey/gui/components/menubar.py
gooey/gui/components/modals.py
gooey/gui/components/sidebar.py
gooey/gui/components/tabbar.py
gooey/gui/components/layouts/__init__.py
gooey/gui/components/layouts/layouts.py
gooey/gui/components/util/__init__.py
gooey/gui/components/util/wrapped_static_text.py
gooey/gui/components/widgets/__init__.py
gooey/gui/components/widgets/bases.py
gooey/gui/components/widgets/basictextconsole.py
gooey/gui/components/widgets/beep_boop.py
gooey/gui/components/widgets/checkbox.py
gooey/gui/components/widgets/choosers.py
gooey/gui/components/widgets/command.py
gooey/gui/components/widgets/counter.py
gooey/gui/components/widgets/dropdown.py
gooey/gui/components/widgets/listbox.py
gooey/gui/components/widgets/password.py
gooey/gui/components/widgets/radio_group.py
gooey/gui/components/widgets/richtextconsole.py
gooey/gui/components/widgets/textarea.py
gooey/gui/components/widgets/textfield.py
gooey/gui/components/widgets/core/__init__.py
gooey/gui/components/widgets/core/chooser.py
gooey/gui/components/widgets/core/text_input.py
gooey/gui/components/widgets/dialogs/__init__.py
gooey/gui/components/widgets/dialogs/calender_dialog.py
gooey/gui/containers/__init__.py
gooey/gui/containers/application.py
gooey/gui/lang/__init__.py
gooey/gui/lang/i18n.py
gooey/gui/lang/i18n_config.py
gooey/gui/util/__init__.py
gooey/gui/util/casting.py
gooey/gui/util/filedrop.py
gooey/gui/util/freeze.py
gooey/gui/util/functional.py
gooey/gui/util/quoting.py
